./.gitignore
./PKG-INFO
./README.md
./pyproject.toml
./schema.sql
./bottle_cli/__init__.py
bottle_cli-0.1.0.dist-info/METADATA
bottle_cli-0.1.0.dist-info/WHEEL
bottle_cli-0.1.0.dist-info/entry_points.txt
bottle_cli-0.1.0.dist-info/RECORD
