Metadata-Version: 2.4
Name: bottle-cli
Version: 0.1.0
Summary: Get human feedback on your projects - message in a bottle for developers
Project-URL: Homepage, https://github.com/yourusername/bottle-cli
Project-URL: Repository, https://github.com/yourusername/bottle-cli
Author-email: Your Name <you@example.com>
License-Expression: MIT
Keywords: cli,code-review,developer-tools,feedback
Classifier: Development Status :: 3 - Alpha
Classifier: Environment :: Console
Classifier: Intended Audience :: Developers
Classifier: License :: OSI Approved :: MIT License
Classifier: Programming Language :: Python :: 3
Classifier: Programming Language :: Python :: 3.9
Classifier: Programming Language :: Python :: 3.10
Classifier: Programming Language :: Python :: 3.11
Classifier: Programming Language :: Python :: 3.12
Requires-Python: >=3.9
Requires-Dist: google-generativeai>=0.5.0
Requires-Dist: rich>=13.0.0
Requires-Dist: supabase>=2.0.0
Requires-Dist: typer>=0.9.0
